isentia_common/__init__.py
isentia_common/__version__.py
isentia_common/log.py
isentia_common_python-1.1.0.dist-info/METADATA
isentia_common_python-1.1.0.dist-info/WHEEL
isentia_common_python-1.1.0.dist-info/top_level.txt
isentia_common_python-1.1.0.dist-info/RECORD
