Metadata-Version: 2.1
Name: isentia-common-python
Version: 1.1.0
Summary: UNKNOWN
Home-page: UNKNOWN
Author: Isentia
License: UNKNOWN
Platform: UNKNOWN
Requires-Python: >=3.7
Requires-Dist: python-json-logger (==0.1.11)
